bar/speaker.py
dateuploader-1.0.0.dist-info/DESCRIPTION.rst
dateuploader-1.0.0.dist-info/METADATA
dateuploader-1.0.0.dist-info/RECORD
dateuploader-1.0.0.dist-info/WHEEL
dateuploader-1.0.0.dist-info/metadata.json
dateuploader-1.0.0.dist-info/top_level.txt
