Metadata-Version: 2.0
Name: dateuploader
Version: 1.0.0
Summary: pypi test pkg
Home-page: https://e.coding.net/codingcorp/coding-artifacts-demo.git
Author: ericchan77
Author-email: 1305584643@qq.com
License: MIT
Download-URL: https://codingcorp.coding.net/p/mayday/artifacts/297/pypi/package/471/version/5772
Keywords: PyPI,artifacts,Python
Platform: UNKNOWN
License-File: LICENSE.txt
